datatensor.py
datatensor-0.2.1.dist-info/METADATA
datatensor-0.2.1.dist-info/WHEEL
datatensor-0.2.1.dist-info/top_level.txt
datatensor-0.2.1.dist-info/RECORD
