Metadata-Version: 2.4
Name: datatensor
Version: 0.2.1
Summary: Lightweight library 
Home-page: https://pypi.org/project/DataTensor/
Author: Iyazkasep
Author-email: iyaz.kasep2009@gmail.com
Classifier: Programming Language :: Python :: 3
Classifier: License :: OSI Approved :: MIT License
Classifier: Operating System :: OS Independent
Requires-Python: >=3.8
Requires-Dist: numpy>=1.24.0
Dynamic: author
Dynamic: author-email
Dynamic: classifier
Dynamic: description
Dynamic: description-content-type
Dynamic: home-page
Dynamic: requires-dist
Dynamic: requires-python
Dynamic: summary
